pydtalite_bin/DTALite.dll
pydtalite_bin/DTALite.so
pydtalite_bin/DTALite_arm.dylib
pydtalite_bin/DTALite_x86.dylib
pydtalite_bin/__init__.py
pydtalite_bin/path_engine.dll
pydtalite_bin/path_engine.so
pydtalite_bin/path_engine_arm.dylib
pydtalite_bin/path_engine_x86.dylib
DLSim-0.2.12.dist-info/METADATA
DLSim-0.2.12.dist-info/WHEEL
DLSim-0.2.12.dist-info/top_level.txt
DLSim-0.2.12.dist-info/RECORD
