Metadata-Version: 2.1
Name: DLSim
Version: 0.2.12
Summary: DLSim is an open-source, cross-platform, lightweight, and fast Python traffic assignment tool adopted and modified from ASU TransAI Lab
Home-page: https://github.com/asu-trans-ai-lab/DLSim
Author: Dr.Xuesong (Simon) Zhou, Dr.Cafer Avci, Xiangyong Luo
Author-email: xzhou74@asu.edu, luoxiangyong01@gmail.com
Classifier: License :: OSI Approved :: Apache Software License
Classifier: Operating System :: OS Independent
Classifier: Programming Language :: Python :: 3
Classifier: Programming Language :: Python :: Implementation :: PyPy
